statsu/__init__.py
statsu/__main__.py
statsu/core.py
statsu/statsu.py
statsu/actions/__init__.py
statsu/actions/action_base.py
statsu/actions/action_edit.py
statsu/actions/action_file.py
statsu/actions/settings.py
statsu/data/__init__.py
statsu/data/data_model.py
statsu/data/file_loader.py
statsu/data/file_manager.py
statsu/ui/__init__.py
statsu/ui/data_container.py
statsu/ui/dialog.py
statsu/ui/main_window.py
statsu/ui/user_command.py
statsu/ui/design/__init__.py
statsu/ui/design/data_container.py
statsu/ui/design/main_window.py
statsu/ui/design/open_csv_dialog.py
statsu-0.0.12.dist-info/LICENSE
statsu-0.0.12.dist-info/METADATA
statsu-0.0.12.dist-info/WHEEL
statsu-0.0.12.dist-info/top_level.txt
statsu-0.0.12.dist-info/RECORD
