Metadata-Version: 2.1
Name: statsu
Version: 0.0.12
Summary: Pandas Dataframe Editor
Home-page: https://github.com/ysb06/statsu
Author: sbyim
Author-email: ysb06@hotmail.com
License: MIT License        
License-File: LICENSE
Requires-Dist: PySide6
Requires-Dist: pandas
Requires-Dist: openpyxl
